{
  "post_comments.post_id": "community_posts.id",
  "post_comments.parent_id": "post_comments.id",
  "emergency_info.city_id": "cities.id",
  "ai_messages.conversation_id": "ai_conversations.id",
  "restaurants.city_id": "cities.id",
  "check_ins.city_id": "cities.id",
  "check_ins.attraction_id": "attractions.id",
  "check_ins.restaurant_id": "restaurants.id",
  "city_metrics.city_id": "cities.id",
  "city_scores.city_id": "cities.id",
  "ai_conversations.city_id": "cities.id",
  "city_images.city_id": "cities.id",
  "scam_reports.city_id": "cities.id",
  "city_score_history.city_id": "cities.id",
  "post_likes.post_id": "community_posts.id",
  "community_posts.city_id": "cities.id",
  "attractions.city_id": "cities.id",
  "blogger_restaurants.restaurant_id": "restaurants.id",
  "blogger_restaurants.city_id": "cities.id",
  "city_source_data.city_id": "cities.id",
  "price_references.city_id": "cities.id",
  "itinerary_days.itinerary_id": "itineraries.id",
  "itinerary_days.city_id": "cities.id"
}